cv2/__init__.py
cv2/__init__.pyi
cv2/config-3.10.py
cv2/config.py
cv2/load_config_py2.py
cv2/load_config_py3.py
cv2/py.typed
iva_cv-0.1.3.dist-info/METADATA
iva_cv-0.1.3.dist-info/WHEEL
iva_cv-0.1.3.dist-info/top_level.txt
iva_cv-0.1.3.dist-info/RECORD
