Metadata-Version: 2.1
Name: iva-cv
Version: 0.1.3
Summary: Custom OpenCV with FFmpeg & GStreamer support
Home-page: https://geniusvision.in
Author: GVD-Clarify-IVA
Author-email: herambmishra@geniusvision.in
License: UNKNOWN
Platform: UNKNOWN
Classifier: Programming Language :: Python :: 3
Classifier: Operating System :: POSIX :: Linux
Requires-Python: >=3.6
